rfccsv/__init__.py
rfccsv/validator.py
rfccsv-0.2.0.dist-info/METADATA
rfccsv-0.2.0.dist-info/WHEEL
rfccsv-0.2.0.dist-info/RECORD
