Metadata-Version: 2.1
Name: rfccsv
Version: 0.2.0
Summary: A simple RFC 4180 CSV validator.
Home-page: https://github.com/trygu/rfccsv
License: MIT
Author: Trygve Falch
Author-email: trygve.falch@gmail.com
Requires-Python: >=3.11,<4.0
Classifier: License :: OSI Approved :: MIT License
Classifier: Programming Language :: Python :: 3
Classifier: Programming Language :: Python :: 3.11
Project-URL: Repository, https://github.com/trygu/rfccsv
